webint_posts/__init__.py
webint_posts/templates/__init__.py
webint_posts/templates/access_denied.html
webint_posts/templates/activity.html
webint_posts/templates/card.html
webint_posts/templates/cards.html
webint_posts/templates/channel.html
webint_posts/templates/channels.html
webint_posts/templates/day.html
webint_posts/templates/entries.html
webint_posts/templates/entry.html
webint_posts/templates/entry_not_found.html
webint_posts/templates/month.html
webint_posts/templates/render_dict.html
webint_posts/templates/rooms.html
webint_posts/templates/syndication.html
webint_posts/templates/year.html
webint_posts-0.0.26.dist-info/METADATA
webint_posts-0.0.26.dist-info/entry_points.txt
webint_posts-0.0.26.dist-info/WHEEL
webint_posts-0.0.26.dist-info/RECORD
